psiturk/__init__.py
psiturk/__main__.py
psiturk/amt_services.py
psiturk/amt_services_wrapper.py
psiturk/command_line.py
psiturk/db.py
psiturk/do_heroku_setup.py
psiturk/experiment.py
psiturk/experiment_errors.py
psiturk/experiment_server.py
psiturk/experiment_server_controller.py
psiturk/models.py
psiturk/psiturk_config.py
psiturk/psiturk_exceptions.py
psiturk/psiturk_shell.py
psiturk/psiturk_statuses.py
psiturk/services_manager.py
psiturk/setup_example.py
psiturk/tasks.py
psiturk/user_utils.py
psiturk/utils.py
psiturk/version.py
psiturk/api/__init__.py
psiturk/dashboard/__init__.py
psiturk/dashboard/static/js/assignments.js
psiturk/dashboard/static/js/campaigns.js
psiturk/dashboard/static/js/flash_messages.js
psiturk/dashboard/static/js/hits.js
psiturk/dashboard/static/js/index.js
psiturk/dashboard/static/js/layout.js
psiturk/dashboard/static/js/tasks.js
psiturk/dashboard/static/styles/base.css
psiturk/dashboard/static/styles/layout.css
psiturk/dashboard/templates/dashboard/assignments.html
psiturk/dashboard/templates/dashboard/base.html
psiturk/dashboard/templates/dashboard/campaigns.html
psiturk/dashboard/templates/dashboard/flashed_messages.html
psiturk/dashboard/templates/dashboard/hits.html
psiturk/dashboard/templates/dashboard/index.html
psiturk/dashboard/templates/dashboard/login.html
psiturk/dashboard/templates/dashboard/mode.html
psiturk/dashboard/templates/dashboard/tasks.html
psiturk/dashboard/templates/dashboard/layouts/layout.html
psiturk/default_configs/cloud_config_defaults.txt
psiturk/default_configs/global_config_defaults.txt
psiturk/default_configs/local_config_defaults.txt
psiturk/example/advanced_quals.json.sample
psiturk/example/config.txt.sample
psiturk/example/custom.py.sample
psiturk/example/static/favicon.ico
psiturk/example/static/css/bootstrap.min.css
psiturk/example/static/css/style.css
psiturk/example/static/fonts/glyphicons-halflings-regular.eot
psiturk/example/static/fonts/glyphicons-halflings-regular.svg
PsiTurk-3.3.1.dist-info/LICENSE
PsiTurk-3.3.1.dist-info/METADATA
PsiTurk-3.3.1.dist-info/WHEEL
PsiTurk-3.3.1.dist-info/entry_points.txt
PsiTurk-3.3.1.dist-info/top_level.txt
PsiTurk-3.3.1.dist-info/RECORD
