Metadata-Version: 2.1
Name: PsiTurk
Version: 3.3.1
Summary: An open platform for science on Amazon Mechanical Turk
Home-page: https://github.com/NYUCCL/psiturk
Author: NYU Computation and Cognition Lab
Author-email: authors@psiturk.org
Classifier: Programming Language :: Python
Classifier: Programming Language :: Python :: 3
Classifier: Programming Language :: Python :: 3.6
Classifier: Programming Language :: Python :: 3.7
License-File: LICENSE
Requires-Dist: Flask-RESTful (~=0.3.7)
Requires-Dist: boto3 (~=1.9.179)
Requires-Dist: fuzzywuzzy (~=0.17.0)
Requires-Dist: cmd2 (~=0.9.14)
Requires-Dist: psutil (~=5.6.3)
Requires-Dist: Flask-Login (~=0.4.1)
Requires-Dist: gunicorn[gevent] (~=20.0.4)
Requires-Dist: Flask (~=1.1.4)
Requires-Dist: itsdangerous (~=1.1.0)
Requires-Dist: markupsafe (~=2.0.1)
Requires-Dist: certifi (~=2019.11.28)
Requires-Dist: pytz (~=2019.1)
Requires-Dist: user-agents (~=2.0)
Requires-Dist: docopt (~=0.6.2)
Requires-Dist: urllib3 (~=1.25.3)
Requires-Dist: Faker (~=1.0.7)
Requires-Dist: requests (~=2.22.0)
Requires-Dist: APScheduler (~=3.6.1)
Requires-Dist: botocore (~=1.12.179)
Requires-Dist: SQLAlchemy (~=1.3.5)
Requires-Dist: pytest (~=6.1.1)
Requires-Dist: future (~=0.17.1)
Requires-Dist: GitPython (~=3.1.0)
Requires-Dist: python-dotenv (~=0.12.0)
Requires-Dist: python-dateutil (~=2.8.1)
Requires-Dist: pyOpenSSL (~=22.0.0)
Requires-Dist: setproctitle (~=1.1.10)
Provides-Extra: dev
Requires-Dist: sphinx ; extra == 'dev'
Requires-Dist: sphinx-rtd-theme ; extra == 'dev'
Requires-Dist: sphinx-server ; extra == 'dev'
Provides-Extra: testing
Requires-Dist: pytest ; extra == 'testing'
Requires-Dist: ciso8601 (~=2.1.3) ; extra == 'testing'
Requires-Dist: pytest-mock ; extra == 'testing'
Requires-Dist: pytest-socket ; extra == 'testing'
Requires-Dist: pytz ; extra == 'testing'
